badminton/__init__.py
badminton/replay.py
badminton-0.0.8.dist-info/METADATA
badminton-0.0.8.dist-info/WHEEL
badminton-0.0.8.dist-info/entry_points.txt
badminton-0.0.8.dist-info/top_level.txt
badminton-0.0.8.dist-info/RECORD
