Metadata-Version: 2.1
Name: badminton
Version: 0.0.8
Summary: Badminton data
Home-page: https://github.com/microprediction/badminton
Author: microprediction
Author-email: info@microprediction.org
License: MIT
Platform: UNKNOWN
Classifier: License :: OSI Approved :: MIT License
Classifier: Programming Language :: Python :: 3
Classifier: Programming Language :: Python :: 3.7
Requires-Dist: getjson
